aiscan/__init__.py
aiscan/__main__.py
aiscan-0.1.0.dist-info/LICENSE
aiscan-0.1.0.dist-info/METADATA
aiscan-0.1.0.dist-info/WHEEL
aiscan-0.1.0.dist-info/entry_points.txt
aiscan-0.1.0.dist-info/top_level.txt
aiscan-0.1.0.dist-info/RECORD
