Metadata-Version: 2.1
Name: aiscan
Version: 0.1.0
Summary: Scan AI models for problems
Home-page: https://github.com/IQTLabs/aiscan
Author: JJ Ben-Joseph
Author-email: jbenjoseph@iqt.org
License: Apache
Keywords: machine_learning artificial_intelligence
Platform: UNKNOWN
Classifier: Topic :: Scientific/Engineering :: Artificial Intelligence
Classifier: Development Status :: 1 - Planning
Classifier: Intended Audience :: Developers
Classifier: Intended Audience :: Science/Research
Classifier: Programming Language :: Python :: 3 :: Only
Classifier: Operating System :: OS Independent
Requires-Python: >=3.8
Requires-Dist: pandas
Requires-Dist: tabulate
Requires-Dist: torch
Requires-Dist: transformers
Requires-Dist: types-tabulate
